{
    "lunedi": [{
            "ora": "8:10-9:10",
            "materia": "Maraggi"

        }, {
            "ora": "9:10-10:10",
            "materia": "Maraggi"

        }, {
            "ora": "10:15-11:10",
            "materia": "Bertolini"

        }, {
            "ora": "11:10-12:05",
            "materia": "Pozzi"

        }, {
            "ora": "12:15-13:10",
            "materia": "Costa"

        }, {
            "ora": "13:10-14:05",
            "materia": "Costa"

        }
    ],
    "martedi": [{
            "ora": "8:10-9:10",
            "materia": "Maraggi"

        }, {
            "ora": "9:10-10:10",
            "materia": "Martelli"

        }, {
            "ora": "10:15-11:10",
            "materia": "Gnaccolini"

        }, {
            "ora": "11:10-12:05",
            "materia": "Gnaccolini"

        }, {
            "ora": "12:15-13:10",
            "materia": "Pozzi"

        }, {
            "ora": "13:10-14:05",
            "materia": "Cisana/Sciarra/Bertolini"
        }
    ],
    "mercoledi": [{
            "ora": "8:10-9:10",
            "materia": "Maraggi"

        }, {
            "ora": "9:10-10:10",
            "materia": "Maraggi"

        }, {
            "ora": "10:15-11:10",
            "materia": "Bertolini"

        }, {
            "ora": "11:10-12:05",
            "materia": "Pozzi"

        }, {
            "ora": "12:15-13:10",
            "materia": "Penzo"

        }, {
            "ora": "13:10-14:05",
            "materia": "Gnaccolini"

        }
    ],
    "giovedi": [{
            "ora": "8:10-9:10",
            "materia": "Maraggi"

        }, {
            "ora": "9:10-10:10",
            "materia": "Gnaccolini"

        }, {
            "ora": "10:15-11:10",
            "materia": "Gnaccolini"

        }, {
            "ora": "11:10-12:05",
            "materia": "Meli"

        }, {
            "ora": "12:15-13:10",
            "materia": "Meli"

        }, {
            "ora": "13:10-14:05",
            "materia": "Bertolini"

        }
    ],
    "venerdi": [{
            "ora": "8:10-9:00",
            "materia": "Cisana/Sciarra/Bertolini"

        }, {
            "ora": "9:00-9:50",
            "materia": "Gnaccolini"

        }, {
            "ora": "9:50-10:40",
            "materia": "Pozzi"

        }, {
            "ora": "10:50-11:40",
            "materia": "Gnaccolini"

        }, {
            "ora": "11:40-12:30",
            "materia": "Penzo"

        }, {
            "ora": "12:40-13:30",
            "materia": "Marsili"

        }, {
            "ora": "13:30-14:20",
            "materia": "Maraggi"

        }
    ],"eventi": [
        {}    
    ]
}
